fhirizer/__init__.py
fhirizer/cli.py
fhirizer/entity2fhir.py
fhirizer/icgc2fhir.py
fhirizer/mapping.py
fhirizer/schema.py
fhirizer/utils.py
fhirizer/labels/__init__.py
fhirizer/labels/case.py
fhirizer/labels/files.py
fhirizer/labels/project.py
mapping/case.json
mapping/case2.json
mapping/case3.json
mapping/case_test.json
mapping/file.json
mapping/file1.json
mapping/file2.json
mapping/project.json
resources/ncit2mondo.json.gz
resources/gdc_resources/content_annotations/biospecimen/aliquot.json
resources/gdc_resources/content_annotations/biospecimen/analyte.json
resources/gdc_resources/content_annotations/biospecimen/biospecimen_imaging_observation copy.json
resources/gdc_resources/content_annotations/biospecimen/biospecimen_imaging_observation.json
resources/gdc_resources/content_annotations/biospecimen/biospecimen_observation.json
resources/gdc_resources/content_annotations/biospecimen/portion.json
resources/gdc_resources/content_annotations/biospecimen/sample.json
resources/gdc_resources/content_annotations/case/diagnoses_ajcc_pathology_tumor_stage.json
resources/gdc_resources/content_annotations/case/diagnoses_tumor_grade.json
resources/gdc_resources/content_annotations/case/disease_types.json
resources/gdc_resources/content_annotations/case/primary_sites.json
resources/gdc_resources/content_annotations/case/social_history_alcohol_observations.json
resources/gdc_resources/content_annotations/case/social_history_smoking_observations.json
resources/gdc_resources/content_annotations/demographic/ethnicity.json
resources/gdc_resources/content_annotations/demographic/gender.json
resources/gdc_resources/content_annotations/demographic/race.json
resources/gdc_resources/content_annotations/diagnosis/cancer_pathological_staging.json
resources/gdc_resources/content_annotations/diagnosis/classification_of_tumor.json
resources/gdc_resources/data_dictionary/administrative/center.json
resources/gdc_resources/data_dictionary/administrative/program.json
fhirizer-2.0.0.dist-info/METADATA
fhirizer-2.0.0.dist-info/WHEEL
fhirizer-2.0.0.dist-info/entry_points.txt
fhirizer-2.0.0.dist-info/top_level.txt
fhirizer-2.0.0.dist-info/RECORD
