Metadata-Version: 2.1
Name: fhirizer
Version: 2.0.0
Summary: Mapping GDC's and Cellosaurus schema to FHIR schema.
Home-page: https://github.com/bmeg/fhirizer
Author: https://ellrottlab.org/
Platform: any
Classifier: Development Status :: 3 - Alpha
Classifier: Programming Language :: Python
Classifier: Programming Language :: Python :: 3.9
Classifier: Programming Language :: Python :: 3.10
Classifier: Programming Language :: Python :: 3.11
Classifier: Programming Language :: Python :: 3.12
Classifier: License :: OSI Approved :: MIT License
Classifier: Intended Audience :: Developers
Classifier: Intended Audience :: Science/Research
Classifier: Topic :: Scientific/Engineering
Classifier: Topic :: Scientific/Engineering :: Bio-Informatics
Requires-Python: >=3.9, <4.0
Requires-Dist: charset-normalizer
Requires-Dist: idna
Requires-Dist: certifi
Requires-Dist: requests
Requires-Dist: pydantic
Requires-Dist: pytest
Requires-Dist: click
Requires-Dist: pathlib
Requires-Dist: orjson
Requires-Dist: tqdm
Requires-Dist: uuid
Requires-Dist: openpyxl
Requires-Dist: pandas
Requires-Dist: inflection
Requires-Dist: iteration-utilities
Requires-Dist: icd10-cm
Requires-Dist: beautifulsoup4
Requires-Dist: gen3-tracker >=0.0.4rc36
Requires-Dist: fhir.resources >=7.1.0
